{
    "version": "2.15.6",
    "description": "Multi-Platform Package Manager for Stable Diffusion",
    "license": {
        "identifier": "AGPL-3.0",
        "url": "https://github.com/LykosAI/StabilityMatrix?tab=AGPL-3.0-1-ov-file"
    },
    "url": "https://github.com/LykosAI/StabilityMatrix/releases/download/v2.15.6/StabilityMatrix-win-x64.zip",
    "homepage": "https://github.com/LykosAI/StabilityMatrix",
    "hash": "54366ce6298cf06b1e54b61bed33f1280d9e0cfe46a9dcab5e0f4ab657297170",
    "bin": "StabilityMatrix.exe",
    "shortcuts": [
        [
            "StabilityMatrix.exe",
            "StabilityMatrix"
        ]
    ],
    "persist": "Data",
    "checkver": {
        "github": "https://github.com/LykosAI/StabilityMatrix"
    },
    "autoupdate": {
        "url": "https://github.com/LykosAI/StabilityMatrix/releases/download/v$version/StabilityMatrix-win-x64.zip"
    }
}
